DirCat/__init__.py
DirCat/config.py
DirCat/main.py
dircat-0.2.0.dist-info/licenses/LICENSE
dircat-0.2.0.dist-info/METADATA
dircat-0.2.0.dist-info/WHEEL
dircat-0.2.0.dist-info/entry_points.txt
dircat-0.2.0.dist-info/top_level.txt
dircat-0.2.0.dist-info/RECORD
