Metadata-Version: 2.4
Name: DirCat
Version: 0.2.0
Summary: 一个将目录结构和文件内容复制到剪切板的工具
Home-page: https://github.com/ENOCH-lyn/DirCat
Author: ENOCH
Author-email: enoch@enoch.host
Classifier: Programming Language :: Python :: 3
Classifier: License :: OSI Approved :: MIT License
Classifier: Operating System :: OS Independent
Requires-Python: >=3.6
License-File: LICENSE
Requires-Dist: pyperclip
Dynamic: author
Dynamic: author-email
Dynamic: classifier
Dynamic: description
Dynamic: description-content-type
Dynamic: home-page
Dynamic: license-file
Dynamic: requires-dist
Dynamic: requires-python
Dynamic: summary
